{
  "records": [
    {
      "title": "Pop",
      "artist": "Madonna",
      "year": 1990,
      "iamge": "path to my image",
      "price": 15,
      "id": "1636966511849"
    }
  ],
  "users": [
    {
      "firstName": "steve",
      "lastName": "stevenson",
      "age": "19",
      "fbw": "38",
      "profession": "Musician",
      "favoriteBands": [
        "Radiohead",
        "Motorhead",
        "Machinehead",
        "The talking heads"
      ],
      "email": "steve@steve.com"
    },
    {
      "firstName": "steve",
      "lastName": "stevenson",
      "age": "19",
      "fbw": "36",
      "profession": "Musician",
      "favoriteBands": [
        "Radiohead",
        "Motorhead",
        "Machinehead",
        "The talking heads"
      ],
      "email": "steve@steve.com"
    },
    {
      "firstName": "steve",
      "lastName": "stevenson",
      "age": "19",
      "fbw": "36",
      "profession": "Musician",
      "favoriteBands": [
        "Radiohead",
        "Motorhead",
        "Machinehead",
        "The talking heads"
      ],
      "email": "steve@steve.com"
    }
  ]
}